tuix/__init__.py
tuix/tuix.py
tuix/appearance/__init__.py
tuix/appearance/appearance.py
tuix/appearance/color_code.py
tuix/appearance/escape_code.py
tuix/appearance/format_code.py
tuix-0.0.6.dist-info/.gitignore
tuix-0.0.6.dist-info/METADATA
tuix-0.0.6.dist-info/WHEEL
tuix-0.0.6.dist-info/top_level.txt
tuix-0.0.6.dist-info/RECORD
