Metadata-Version: 2.4
Name: tuix
Version: 0.0.6
Summary: A Revolution In UI/UX Of Terminal: tuix
Home-page: https://github.com/abolfazlmohammadpour/tuix.git
Author: ABOLFAZL MOHAMMADPOUR
Author-email: ABOLFAZLMOHAMMADPOURQAEMSHAHR@GMAIL.COM
License: MIT
Classifier: Programming Language :: Python :: 3
Classifier: License :: OSI Approved :: MIT License
Classifier: Operating System :: OS Independent
Requires-Python: >=3.10
Dynamic: author
Dynamic: author-email
Dynamic: classifier
Dynamic: description
Dynamic: description-content-type
Dynamic: home-page
Dynamic: license
Dynamic: requires-python
Dynamic: summary
